cosmonaut/__init__.py
cosmonaut/config.py
cosmonaut/core.py
cosmonaut/data_models.py
cosmonaut/logging.py
cosmonaut/cli/__init__.py
cosmonaut/cli/core.py
cosmonaut/clients/__init__.py
cosmonaut/clients/anthropic.py
cosmonaut/clients/base.py
cosmonaut/clients/gemini.py
cosmonaut/clients/openai.py
cosmonaut/clients/selector.py
cosmonaut/processors/__init__.py
cosmonaut/processors/anthropic.py
cosmonaut/processors/base.py
cosmonaut/processors/gemini.py
cosmonaut/processors/openai.py
cosmonaut-0.0.7.dist-info/LICENSE
cosmonaut-0.0.7.dist-info/METADATA
cosmonaut-0.0.7.dist-info/WHEEL
cosmonaut-0.0.7.dist-info/entry_points.txt
cosmonaut-0.0.7.dist-info/top_level.txt
cosmonaut-0.0.7.dist-info/RECORD
