Metadata-Version: 2.1
Name: cosmonaut
Version: 0.0.7
Summary: Helping you find structure in the cosmos of data.
Author-email: Amit Yadav <amit.yadav.iitr@gmail.com>
Maintainer-email: Amit Yadav <amit.yadav.iitr@gmail.com>
License: MIT License
Project-URL: Homepage, https://github.com/am1tyadav/cosmonaut
Project-URL: Bug Tracker, https://github.com/am1tyadav/cosmonaut/issues
Requires-Python: >=3.10
License-File: LICENSE
Requires-Dist: httpx
Requires-Dist: pandas
Requires-Dist: pydantic
Requires-Dist: python-dotenv
Requires-Dist: pyyaml
Requires-Dist: questionary
Provides-Extra: dev
Requires-Dist: pytest; extra == "dev"
Provides-Extra: examples
Requires-Dist: pyspark; extra == "examples"
Requires-Dist: duckdb; extra == "examples"
Provides-Extra: all
Requires-Dist: cosmonaut[dev,examples]; extra == "all"
